{
    "annotations": [
        {
            "tag": "Strafrahmen",
            "category": "Formalia",
            "quote": "Das Gesetz sieht für den Totschlag gemäß § 212 Abs. 1 StGB die Verhängung einer Freiheitsstrafe von fünf bis fünfzehn Jahren vor. In besonders schweren Fällen ist gemäß § 212 Abs. 2 StGB auf lebenslange Freiheitsstrafe zu erkennen. Im minder schweren Fall ist gemäß § 213 StGB ein Strafrahmen eröffnet, der Freiheitsstrafe von einem bis zu zehn Jahren vorsieht."
        },
        {
            "tag": "Tatprovokation",
            "category": "Mildernd",
            "quote": "Zwar machte L2 N abwertende Äußerungen in Bezug auf den Angeklagten als Mann und in der Rolle als Vater. Dabei handelte es sich um eine Provokation, nicht jedoch um eine schwere Beleidigung im Sinne von § 213 1. Alt. StGB."
        },
        {
            "tag": "Gestaendnis",
            "category": "Mildernd",
            "quote": "der Angeklagte bereits frühzeitig in seiner ersten verantwortlichen Vernehmung ein von Reue getragenes Geständnis abgelegt hat, welches dadurch dokumentiert wird, dass er die vernehmenden Polizeibeamten zum Ablageort der Leiche geführt hat, und er dieses Geständnis in der Hauptverhandlung wiederholt hat,"
        },
        {
            "tag": "Vorleben_Positiv",
            "category": "Mildernd",
            "quote": "es sich bei der erlittenen Untersuchungshaft um die erste Freiheitsentziehung handelt, die naturgemäß beeindruckt."
        },
        {
            "tag": "Enthemmung_Psychologie",
            "category": "Mildernd",
            "quote": "er versucht hat, dem Streit durch Rückzug auszuweichen,"
        },
        {
            "tag": "Enthemmung_Psychologie",
            "category": "Mildernd",
            "quote": "er durch die vorangegangene Auseinandersetzung aufgebracht war,"
        },
        {
            "tag": "Strafhoehe",
            "category": "Formalia",
            "quote": "zwölf Jahren"
        },
        {
            "tag": "Strafrahmen",
            "category": "Formalia",
            "quote": "Es ist daher von dem Strafrahmen des § 212 Abs. 1 StGB und damit einem Strafrahmen von fünf bis fünfzehn Jahren Freiheitsstrafe auszugehen."
        },
        {
            "tag": "Motiv_Verwerflich",
            "category": "Schärfend",
            "quote": "er selbstsüchtige Motive insoweit verfolgte, als durch die Tat - mag dies auch einen untergeordneten Beweggrund dargestellt haben - auch finanziellen Folgen einer Trennung begegnet werden sollte."
        },
        {
            "tag": "Tatbild_Brutalitaet",
            "category": "Schärfend",
            "quote": "es sich bei einem Erstickungstod um einen für das Opfer qualvollen Tod handelt,"
        },
        {
            "tag": "Tatbild_Brutalitaet",
            "category": "Schärfend",
            "quote": "es sich nicht um einen schnellen Tod, sondern ein Geschehen handelte, in dem das Opfer längere Zeit Todesangst erleiden musste und den Tod kommen sah,"
        },
        {
            "tag": "Gesamtwuerdigung",
            "category": "Abwägung",
            "quote": "Die Abwägung der vorgenannten Umstände, bei denen die belastenden Momente in ihrem Gewicht deutlich überwiegen, führt dazu, dass ein sonstiger minder schwerer Fall des § 213 Alternative 2 StGB erkennbar nicht vorliegt. Andererseits liegt insbesondere unter Berücksichtigung des frühzeitigen, von Reue getragenen Geständnisses auch ein besonders schwerer Fall des Totschlags im Sinne des § 212 Abs. 2 StGB nicht vor."
        },
        {
            "tag": "Gesamtwuerdigung",
            "category": "Abwägung",
            "quote": "Die im Rahmen der Strafrahmenwahl aufgezeigten für und gegen den Angeklagten sprechenden Faktoren hat die Kammer in Ansehung der getroffenen Feststellungen zur konkreten Strafzumessung nochmals in den Blick genommen."
        },
        {
            "tag": "Strafrahmen",
            "category": "Formalia",
            "quote": "Die Kammer erachtet in dem Regelstrafrahmen des § 212 StGB eine Freiheitsstrafe von zwölf Jahren als tat- und schuldangemessen."
        },
        {
            "tag": "Gesetzesgrundlage",
            "category": "Formalia",
            "quote": "Das Gesetz sieht für den Totschlag gemäß § 212 Abs. 1 StGB die Verhängung einer Freiheitsstrafe von fünf bis fünfzehn Jahren vor. In besonders schweren Fällen ist gemäß § 212 Abs. 2 StGB auf lebenslange Freiheitsstrafe zu erkennen. Im minder schweren Fall ist gemäß § 213 StGB ein Strafrahmen eröffnet, der Freiheitsstrafe von einem bis zu zehn Jahren vorsieht."
        },
        {
            "tag": "Gesetzesgrundlage",
            "category": "Formalia",
            "quote": "§ 212 Abs. 1 StGB"
        },
        {
            "tag": "Gesetzesgrundlage",
            "category": "Formalia",
            "quote": "§ 212 Abs. 2 StGB"
        },
        {
            "tag": "Gesetzesgrundlage",
            "category": "Formalia",
            "quote": "§ 213 StGB"
        },
        {
            "tag": "Gesetzesgrundlage",
            "category": "Formalia",
            "quote": "§ 213 1. Alt. StGB"
        },
        {
            "tag": "Gesetzesgrundlage",
            "category": "Formalia",
            "quote": "§ 213 Alternative 2 StGB"
        },
        {
            "tag": "Gesetzesgrundlage",
            "category": "Formalia",
            "quote": "§ 212 Abs. 1 StGB"
        }
    ]
}